wordcloud-1.9.5.dist-info/RECORD
wordcloud-1.9.5.dist-info/WHEEL
wordcloud-1.9.5.dist-info/entry_points.txt
wordcloud-1.9.5.dist-info/top_level.txt
wordcloud-1.9.5.dist-info/METADATA
wordcloud-1.9.5.dist-info/licenses/LICENSE
wordcloud/wordcloud_cli.py
wordcloud/stopwords
wordcloud/DroidSansMono.ttf
wordcloud/_version.py
wordcloud/__init__.py
wordcloud/tokenization.py
wordcloud/query_integral_image.cpython-311-darwin.so
wordcloud/wordcloud.py
wordcloud/color_from_image.py
wordcloud/__main__.py
wordcloud/query_integral_image.pyx
