Metadata-Version: 2.4
Name: wordcloud
Version: 1.9.5
Summary: A little word cloud generator
Author-email: Andreas Mueller <t3kcit+wordcloud@gmail.com>
License-Expression: MIT
Project-URL: Homepage, https://github.com/amueller/word_cloud
Requires-Python: >=3.9
License-File: LICENSE
Requires-Dist: numpy>=1.19
Requires-Dist: pillow
Requires-Dist: matplotlib
Dynamic: license-file
